zipstream/__init__.py
zipstream/aiozipstream.py
zipstream/consts.py
zipstream/zipstream.py
aiozipstream-0.4.dist-info/METADATA
aiozipstream-0.4.dist-info/WHEEL
aiozipstream-0.4.dist-info/top_level.txt
aiozipstream-0.4.dist-info/RECORD
