Metadata-Version: 2.1
Name: aiozipstream
Version: 0.4
Summary: Creating zip files on the fly
Home-page: https://github.com/kbbdy/zipstream
Author: Krzysztof Babendych
License: BSD
Keywords: zip streaming
Platform: UNKNOWN
Classifier: Intended Audience :: Developers
Classifier: Topic :: Software Development :: Build Tools
Classifier: License :: OSI Approved :: BSD License
Classifier: Programming Language :: Python :: 2
Classifier: Programming Language :: Python :: 2.7
Classifier: Programming Language :: Python :: 3
Classifier: Programming Language :: Python :: 3.6
